runleiden/__init__.py
runleiden/runleiden.py
runleiden-0.0.5.dist-info/entry_points.txt
runleiden-0.0.5.dist-info/WHEEL
runleiden-0.0.5.dist-info/METADATA
runleiden-0.0.5.dist-info/RECORD
